[
    { "sub-class": "proteina", "url": "https://www.blackskullusa.com.br/proteina?page=" },
    { "sub-class": "aminoacidos", "url": "https://www.blackskullusa.com.br/aminoacidos?page=" },
    { "sub-class": "vitaminas minerais", "url": "https://www.blackskullusa.com.br/vitaminas-e-minerais?page=" },
    { "sub-class": "carboidratos", "url": "https://www.blackskullusa.com.br/carboidratos?page=" },
    { "sub-class": "hipercalorico", "url": "https://www.blackskullusa.com.br/hipercalorico?page=" },
    { "sub-class": "Cognicao", "url": "https://www.blackskullusa.com.br/Cognicao?page=" },
    { "sub-class": "snacks bebidas", "url": "https://www.blackskullusa.com.br/snacks-e-bebidas?page=" },
    { "sub-class": "pre-treino", "url": "https://www.blackskullusa.com.br/pre-treino?page=" },
    { "sub-class": "pack", "url": "https://www.blackskullusa.com.br/pack?page=" },
    { "sub-class": "termogenico", "url": "https://www.blackskullusa.com.br/termogenico?page=" },
    { "sub-class": "colostro", "url": "https://www.blackskullusa.com.br/colostro?page=" },
    { "sub-class": "barras proteicas", "url": "https://www.blackskullusa.com.br/barras-proteicas?page=" },
    { "sub-class": "kit", "url": "https://www.blackskullusa.com.br/kits---combos?page="  }
]